PyMergers/__init__.py
PyMergers/main.py
PyMergers/models/pymerger_model.tflite
PyMergers-1.0.1.dist-info/LICENSE
PyMergers-1.0.1.dist-info/METADATA
PyMergers-1.0.1.dist-info/WHEEL
PyMergers-1.0.1.dist-info/entry_points.txt
PyMergers-1.0.1.dist-info/top_level.txt
PyMergers-1.0.1.dist-info/RECORD
