Metadata-Version: 2.1
Name: PyMergers
Version: 1.0.1
Summary: Detect Binary Black Hole mergers from Einstein Telescope data using Deep Convolutional Neural Networks
Home-page: https://github.com/wathela/PyMerger
Author: Wathela Alhassan
Author-email: wathelahamed@gmail.com
License: MIT
Classifier: Programming Language :: Python :: 3
Classifier: License :: OSI Approved :: MIT License
Classifier: Operating System :: OS Independent
Requires-Python: >=3.9
License-File: LICENSE
Requires-Dist: gwpy==3.0.8
Requires-Dist: pycbc==2.6.0
Requires-Dist: scipy==1.13.1
Requires-Dist: tensorflow==2.12.0
Requires-Dist: tqdm==4.66.5
